ChangeLog
MANIFEST.in
README.rst
publish.sh
setup.py
test-install.sh
hiver/__init__.py
hiver/__main__.py
hiver.egg-info/PKG-INFO
hiver.egg-info/SOURCES.txt
hiver.egg-info/dependency_links.txt
hiver.egg-info/requires.txt
hiver.egg-info/top_level.txt
hiver/fb303/FacebookBase.py
hiver/fb303/FacebookService.py
hiver/fb303/__init__.py
hiver/fb303/constants.py
hiver/fb303/ttypes.py
hiver/fb303_scripts/__init__.py
hiver/fb303_scripts/fb303_simple_mgmt.py
hiver/hive_metastore/ThriftHiveMetastore.py
hiver/hive_metastore/__init__.py
hiver/hive_metastore/constants.py
hiver/hive_metastore/ttypes.py
hiver/hive_serde/__init__.py
hiver/hive_serde/constants.py
hiver/hive_serde/ttypes.py
hiver/hive_service/ThriftHive.py
hiver/hive_service/__init__.py
hiver/hive_service/constants.py
hiver/hive_service/ttypes.py
hiver/queryplan/__init__.py
hiver/queryplan/constants.py
hiver/queryplan/ttypes.py