Metadata-Version: 1.0
Name: hiver
Version: 0.2.1
Summary: Hive thrift client
Home-page: https://bitbucket.org/tebeka/hive
Author: Miki Tebeka
Author-email: miki.tebeka@gmail.com
License: MIT
Platform: UNKNOWN
